euispice_coreg/__init__.py
euispice_coreg/hdrshift/__init__.py
euispice_coreg/hdrshift/alignment.py
euispice_coreg/hdrshift/alignment_spice.py
euispice_coreg/hdrshift/alignment_spice_selector.py
euispice_coreg/hdrshift/AlignmentResults.py
euispice_coreg/hdrshift/c_correlate.py
euispice_coreg/hdrshift/test/__init__.py
euispice_coreg/hdrshift/test/co_alignment_results.png
euispice_coreg/hdrshift/test/correlation_results.png
euispice_coreg/hdrshift/test/plot_co_alignment1.jpeg
euispice_coreg/hdrshift/test/plot_co_alignment1_results.jpeg
euispice_coreg/hdrshift/test/plot_co_alignment2.jpeg
euispice_coreg/hdrshift/test/plot_co_alignment2_results.jpeg
euispice_coreg/hdrshift/test/plot_correlation1.jpeg
euispice_coreg/hdrshift/test/plot_correlation2.jpeg
euispice_coreg/hdrshift/test/test_alignment.py
euispice_coreg/hdrshift/test/test_alignment_spice.py
euispice_coreg/hdrshift/test/test_alignment_spice_sunpy.py
euispice_coreg/hdrshift/test/test_alignment_sunpy.py
euispice_coreg/hdrshift/test/test_AlignmentResults.py
euispice_coreg/jitter_correction/jitter_correction_imager.py
euispice_coreg/plot/__init__.py
euispice_coreg/plot/perso.mplstyle
euispice_coreg/plot/plot.py
euispice_coreg/plot/test/__init__.py
euispice_coreg/plot/test/co_alignment.jpeg
euispice_coreg/plot/test/co_alignment2.jpeg
euispice_coreg/plot/test/co_alignment_sunpy.pdf
euispice_coreg/plot/test/correlation.jpeg
euispice_coreg/plot/test/correlation2.jpeg
euispice_coreg/plot/test/test_plot.py
euispice_coreg/pxlshift/__init__.py
euispice_coreg/pxlshift/alignment_pixels.py
euispice_coreg/pxlshift/alignment_spice_pixel.py
euispice_coreg/pxlshift/c_correlate.py
euispice_coreg/pxlshift/test/__init__.py
euispice_coreg/pxlshift/test/test_alignment_pixels.py
euispice_coreg/pxlshift/test/test_alignment_spice_pixels.py
euispice_coreg/selector/__init__.py
euispice_coreg/selector/selector.py
euispice_coreg/selector/selector_eui.py
euispice_coreg/selector/selector_spice.py
euispice_coreg/selector/test/__init__.py
euispice_coreg-0.4.0.dist-info/licenses/LICENCE
euispice_coreg-0.4.0.dist-info/METADATA
euispice_coreg-0.4.0.dist-info/WHEEL
euispice_coreg-0.4.0.dist-info/RECORD
