Metadata-Version: 2.4
Name: euispice-coreg
Version: 0.4.0
Summary: Tools to co-register imagers (including HRI-EUV) and SPICE, on-bord Solar Orbiter. 
License-File: LICENCE
Author: dolliou
Author-email: dolliou@mps.mpg.de
Requires-Python: >=3.11,<4.0
Classifier: Programming Language :: Python :: 3
Classifier: Programming Language :: Python :: 3.11
Classifier: Programming Language :: Python :: 3.12
Classifier: Programming Language :: Python :: 3.13
Classifier: Programming Language :: Python :: 3.14
Requires-Dist: astropy (>=7.0)
Requires-Dist: beautifulsoup4 (>=4.12.3)
Requires-Dist: matplotlib (>=3.8.4)
Requires-Dist: multiprocess (>=0.70.15)
Requires-Dist: numba (>=0.61.0,<0.62.0)
Requires-Dist: numpy (>=1.26.4)
Requires-Dist: opencv-python (>=4.9.0.80)
Requires-Dist: pytest (>=8.1.1)
Requires-Dist: reproject (>=0.14.1,<0.15.0)
Requires-Dist: scipy (>=1.13.0)
Requires-Dist: sunpy[visualization] (>=6.0.4,<7.0.0)
Requires-Dist: tqdm (>=4.66.2)
